geniusrise_databases/__init__.py
geniusrise_databases/arangodb.py
geniusrise_databases/athena.py
geniusrise_databases/azure_table.py
geniusrise_databases/bigquery.py
geniusrise_databases/bigtable.py
geniusrise_databases/cassandra.py
geniusrise_databases/cloud_sql.py
geniusrise_databases/cockroach.py
geniusrise_databases/cosmosdb.py
geniusrise_databases/couchbase.py
geniusrise_databases/db2.py
geniusrise_databases/documentdb.py
geniusrise_databases/dynamodb.py
geniusrise_databases/elasticsearch.py
geniusrise_databases/firestore.py
geniusrise_databases/graphite.py
geniusrise_databases/hbase.py
geniusrise_databases/influxdb.py
geniusrise_databases/kairosdb.py
geniusrise_databases/keyspaces.py
geniusrise_databases/ldap.py
geniusrise_databases/memsql.py
geniusrise_databases/mongodb.py
geniusrise_databases/mysql.py
geniusrise_databases/neo4j.py
geniusrise_databases/nuodb.py
geniusrise_databases/opentsdb.py
geniusrise_databases/oracle.py
geniusrise_databases/postgres.py
geniusrise_databases/presto.py
geniusrise_databases/redis.py
geniusrise_databases/riak.py
geniusrise_databases/spanner.py
geniusrise_databases/sql_server.py
geniusrise_databases/sqlite.py
geniusrise_databases/sybase.py
geniusrise_databases/teradata.py
geniusrise_databases/tidb.py
geniusrise_databases/timescaledb.py
geniusrise_databases/vertica.py
geniusrise_databases/voltdb.py
geniusrise_databases-0.1.4.dist-info/METADATA
geniusrise_databases-0.1.4.dist-info/WHEEL
geniusrise_databases-0.1.4.dist-info/top_level.txt
geniusrise_databases-0.1.4.dist-info/RECORD
