Metadata-Version: 2.1
Name: geniusrise-databases
Version: 0.1.4
Summary: listeners bolts for geniusrise
Home-page: https://github.com/geniusrise/geniusrise-databases
Author: ixaxaar
Author-email: ixaxaar@geniusrise.ai
Project-URL: Bug Reports, https://github.com/geniusrise/geniusrise-databases/issues
Project-URL: Source, https://github.com/geniusrise/geniusrise-databases
Project-URL: Documentation, https://docs.geniusrise.ai/
Keywords: mlops,llm,geniusrise,machine learning,data processing
Classifier: Development Status :: 3 - Alpha
Classifier: Intended Audience :: Developers
Classifier: Topic :: Software Development :: Build Tools
Classifier: License :: OSI Approved :: GNU Affero General Public License v3
Classifier: Programming Language :: Python :: 3.10
Classifier: Programming Language :: Python :: 3.11
Classifier: Operating System :: OS Independent
Requires-Python: >=3.10
Requires-Dist: annotated-types (==0.5.0)
Requires-Dist: ansicolors (==1.1.8)
Requires-Dist: arango (==0.2.1)
Requires-Dist: argparse-color-formatter (==1.2.2.post2)
Requires-Dist: async-timeout (==4.0.3)
Requires-Dist: azure-common (==1.1.28)
Requires-Dist: azure-core (==1.29.4)
Requires-Dist: azure-cosmos (==4.5.1)
Requires-Dist: azure-cosmosdb-nspkg (==2.0.2)
Requires-Dist: azure-cosmosdb-table (==1.0.6)
Requires-Dist: azure-nspkg (==3.0.2)
Requires-Dist: basho-erlastic (==2.1.1)
Requires-Dist: bcrypt (==4.0.1)
Requires-Dist: black (==23.7.0)
Requires-Dist: bleach (==6.0.0)
Requires-Dist: boto3 (==1.28.25)
Requires-Dist: botocore (==1.31.25)
Requires-Dist: build (==0.10.0)
Requires-Dist: cachetools (==5.3.1)
Requires-Dist: cassandra-driver (==3.28.0)
Requires-Dist: certifi (==2023.7.22)
Requires-Dist: cffi (==1.15.1)
Requires-Dist: charset-normalizer (==3.2.0)
Requires-Dist: click (==8.1.7)
Requires-Dist: colorama (==0.4.6)
Requires-Dist: colorlog (==6.7.0)
Requires-Dist: couchbase (==4.1.8)
Requires-Dist: coverage (==7.3.0)
Requires-Dist: cryptography (==41.0.3)
Requires-Dist: cx-Oracle (==8.3.0)
Requires-Dist: direnv (==2020.12.3)
Requires-Dist: dnspython (==2.4.2)
Requires-Dist: docopt (==0.6.2)
Requires-Dist: docutils (==0.20.1)
Requires-Dist: elastic-transport (==8.4.0)
Requires-Dist: elasticsearch (==8.9.0)
Requires-Dist: emoji (==2.7.0)
Requires-Dist: env-file (==2020.12.3)
Requires-Dist: exceptiongroup (==1.1.2)
Requires-Dist: flake8 (==6.1.0)
Requires-Dist: geniusrise (==0.0.3)
Requires-Dist: geomet (==0.2.1.post1)
Requires-Dist: google-api-core (==2.11.1)
Requires-Dist: google-auth (==2.17.3)
Requires-Dist: google-cloud-bigquery (==3.11.4)
Requires-Dist: google-cloud-bigtable (==2.21.0)
Requires-Dist: google-cloud-core (==2.3.3)
Requires-Dist: google-cloud-spanner (==3.40.1)
Requires-Dist: google-crc32c (==1.5.0)
Requires-Dist: google-resumable-media (==2.6.0)
Requires-Dist: googleapis-common-protos (==1.60.0)
Requires-Dist: grpc-google-iam-v1 (==0.12.6)
Requires-Dist: grpcio (==1.58.0)
Requires-Dist: grpcio-status (==1.58.0)
Requires-Dist: happybase (==1.2.0)
Requires-Dist: hdfs (==2.7.2)
Requires-Dist: ibm-db (==3.2.0)
Requires-Dist: idna (==3.4)
Requires-Dist: importlib-metadata (==6.8.0)
Requires-Dist: influxdb (==5.3.1)
Requires-Dist: iniconfig (==2.0.0)
Requires-Dist: ipaddress (==1.0.23)
Requires-Dist: jaraco.classes (==3.3.0)
Requires-Dist: jeepney (==0.8.0)
Requires-Dist: jmespath (==0.10.0)
Requires-Dist: jsonpickle (==3.0.1)
Requires-Dist: kafka-python (==2.0.2)
Requires-Dist: keyring (==24.2.0)
Requires-Dist: kubernetes (==27.2.0)
Requires-Dist: ldap3 (==2.9.1)
Requires-Dist: markdown-it-py (==3.0.0)
Requires-Dist: mccabe (==0.7.0)
Requires-Dist: mdurl (==0.1.2)
Requires-Dist: memsql (==3.2.0)
Requires-Dist: mock (==5.1.0)
Requires-Dist: more-itertools (==10.1.0)
Requires-Dist: msgpack (==1.0.5)
Requires-Dist: mypy (==1.5.0)
Requires-Dist: mypy-extensions (==1.0.0)
Requires-Dist: mysqlclient (==2.2.0)
Requires-Dist: neo4j (==5.12.0)
Requires-Dist: nose (==1.3.7)
Requires-Dist: oauthlib (==3.2.2)
Requires-Dist: opentsdb-py (==0.6.0)
Requires-Dist: packaging (==23.1)
Requires-Dist: paramiko (==3.3.1)
Requires-Dist: pathspec (==0.11.2)
Requires-Dist: pkginfo (==1.9.6)
Requires-Dist: platformdirs (==3.10.0)
Requires-Dist: pluggy (==1.2.0)
Requires-Dist: ply (==3.11)
Requires-Dist: presto-python-client (==0.8.4)
Requires-Dist: prettytable (==3.8.0)
Requires-Dist: prometheus-client (==0.17.1)
Requires-Dist: proto-plus (==1.22.3)
Requires-Dist: protobuf (==4.24.3)
Requires-Dist: psutil (==5.9.5)
Requires-Dist: psycopg2 (==2.9.7)
Requires-Dist: pyasn1 (==0.5.0)
Requires-Dist: pyasn1-modules (==0.3.0)
Requires-Dist: pycodestyle (==2.11.0)
Requires-Dist: pycparser (==2.21)
Requires-Dist: pydantic (==2.1.1)
Requires-Dist: pydantic-core (==2.4.0)
Requires-Dist: pyflakes (==3.1.0)
Requires-Dist: Pygments (==2.16.1)
Requires-Dist: PyJWT (==2.8.0)
Requires-Dist: pymongo (==4.5.0)
Requires-Dist: pymssql (==2.2.8)
Requires-Dist: PyMySQL (==1.1.0)
Requires-Dist: PyNaCl (==1.5.0)
Requires-Dist: pynuodb (==2.6.0)
Requires-Dist: pyodbc (==4.0.39)
Requires-Dist: pyproject-hooks (==1.0.0)
Requires-Dist: pytest (==7.4.0)
Requires-Dist: python-arango (==7.6.2)
Requires-Dist: python-dateutil (==2.8.2)
Requires-Dist: python-ldap (==3.4.3)
Requires-Dist: python3-protobuf (==2.5.0)
Requires-Dist: pytz (==2023.3.post1)
Requires-Dist: PyYAML (==6.0.1)
Requires-Dist: readme-renderer (==40.0)
Requires-Dist: redis (==4.6.0)
Requires-Dist: requests (==2.31.0)
Requires-Dist: requests-oauthlib (==1.3.1)
Requires-Dist: requests-toolbelt (==1.0.0)
Requires-Dist: retrying (==1.3.4)
Requires-Dist: rfc3986 (==2.0.0)
Requires-Dist: riak (==2.7.0)
Requires-Dist: rich (==13.5.2)
Requires-Dist: rich-argparse (==1.3.0)
Requires-Dist: rsa (==4.9)
Requires-Dist: s3transfer (==0.6.1)
Requires-Dist: SecretStorage (==3.3.3)
Requires-Dist: shortuuid (==1.0.11)
Requires-Dist: simplejson (==3.19.1)
Requires-Dist: six (==1.16.0)
Requires-Dist: sqlparse (==0.4.4)
Requires-Dist: termcolor (==2.3.0)
Requires-Dist: thriftpy2 (==0.4.16)
Requires-Dist: tomli (==2.0.1)
Requires-Dist: twine (==4.0.2)
Requires-Dist: types-PyMySQL (==1.1.0.1)
Requires-Dist: types-pyOpenSSL (==23.2.0.2)
Requires-Dist: types-redis (==4.6.0.6)
Requires-Dist: typing-extensions (==4.7.1)
Requires-Dist: urllib3 (==1.26.16)
Requires-Dist: values (==2020.12.3)
Requires-Dist: vertica-python (==1.3.5)
Requires-Dist: wcwidth (==0.2.6)
Requires-Dist: webencodings (==0.5.1)
Requires-Dist: websocket-client (==1.6.1)
Requires-Dist: Wraptor (==0.7.0)
Requires-Dist: zipp (==3.16.2)
Provides-Extra: dev
Requires-Dist: check-manifest ; extra == 'dev'
Provides-Extra: test
Requires-Dist: coverage ; extra == 'test'
